[{"timestamp": "1284447600", "speakers": [{"name": "Steven Newhouse"}], "location": "Archief Damrakzijde", "id": "130", "title": "Project Meeting (Private)"}, {"timestamp": "1284453000", "speakers": [], "location": "Grote zaal", "id": "2", "title": "Coffee / Tea"}, {"timestamp": "1284454800", "speakers": [], "location": "Yakult Room", "id": "3", "title": "Opening & Welcome"}, {"timestamp": "1284460200", "speakers": [], "location": "Grote zaal", "id": "5", "title": "Lunch"}, {"timestamp": "1284465600", "speakers": [{"name": "Bob Jones"}, {"name": "Alex Hardisty"}], "location": "Yakult Room", "id": "6", "title": "EEF Requirements and the ESFRI projects: Biological Medical Sciences (BMS) Projects"}, {"timestamp": "1284465600", "speakers": [{"name": "Tiziana Ferrari"}], "location": "Graanbeurszaal", "id": "9", "title": "EGI Production Infrastructure"}, {"timestamp": "1284465600", "speakers": [{"name": "Cecile Germain-Renaud"}], "location": "Verwey", "id": "10", "title": "Instrumenting the Infrastructure"}, {"timestamp": "1284465600", "speakers": [{"name": "John White"}, {"name": "Christoph Witzig"}], "location": "Berlage", "id": "11", "title": "AAI Needs of the DCIs"}, {"timestamp": "1284465600", "speakers": [{"name": "Steven Newhouse"}], "location": "Derkindern", "id": "16", "title": "EGI-InSPIRE External Advisory Committee (Closed)"}, {"timestamp": "1284465600", "speakers": [{"name": "Mingchao Ma"}], "location": "Mendes da Costa", "id": "21", "title": "EGI CISRT F2F (Closed)"}, {"timestamp": "1284465600", "speakers": [{"name": "Gergely Sipos"}], "location": "Keurzaal", "id": "124", "title": "User Training - Getting started in EGI"}, {"timestamp": "1284471000", "speakers": [], "location": "Grote zaal", "id": "17", "title": "Coffee / Tea"}, {"timestamp": "1284472800", "speakers": [{"name": "Mingchao Ma"}], "location": "Mendes da Costa", "id": "21", "title": "EGI CISRT F2F (Closed)"}, {"timestamp": "1284472800", "speakers": [{"name": "John White"}, {"name": "Christoph Witzig"}], "location": "Berlage", "id": "11", "title": "AAI Needs of the DCIs"}, {"timestamp": "1284472800", "speakers": [{"name": "Bob Jones"}, {"name": "Alex Hardisty"}], "location": "Yakult Room", "id": "6", "title": "EEF Requirements and the ESFRI projects: Social Sciences and Humanities (SSH) Projects"}, {"timestamp": "1284472800", "speakers": [{"name": "Steven Newhouse"}], "location": "Keurzaal", "id": "56", "title": "Software Provisioning in EGI"}, {"timestamp": "1284472800", "speakers": [{"name": "Cecile Germain-Renaud"}], "location": "Verwey", "id": "10", "title": "Instrumenting the Infrastructure"}, {"timestamp": "1284472800", "speakers": [{"name": "Michaela Lechner"}], "location": "Graanbeurszaal", "id": "98", "title": "Grid Operations Interoperations"}, {"timestamp": "1284472800", "speakers": [{"name": "celine bitoune"}], "location": "Derkindern", "id": "132", "title": "Private Meeting"}, {"timestamp": "1284534000", "speakers": [], "location": "Yakult Room", "id": "28", "title": "Plenary Keynote"}, {"timestamp": "1284539400", "speakers": [], "location": "Grote zaal", "id": "30", "title": "Coffee / Tea"}, {"timestamp": "1284541200", "speakers": [{"name": "Marios Chatziangelou"}], "location": "Berlage", "id": "8", "title": "EGI User Support Services"}, {"timestamp": "1284541200", "speakers": [{"name": "Peter Szegedi"}, {"name": "Brook Schofield"}], "location": "Mendes da Costa", "id": "32", "title": "TERENA NRENs and Grids Workshop"}, {"timestamp": "1284541200", "speakers": [{"name": "Steven Newhouse"}, {"name": "Silvana Muscella"}, {"name": "Sergio Andreozzi"}], "location": "Graanbeurszaal", "id": "34", "title": "The DCI Projects: Roadmap and Interactions"}, {"timestamp": "1284541200", "speakers": [{"name": "Bob Jones"}, {"name": "Alex Hardisty"}], "location": "Yakult Room", "id": "6", "title": "EEF Requirements and the ESFRI projects: Environmental (ENV) Projects"}, {"timestamp": "1284541200", "speakers": [{"name": "Linda Cornwall"}], "location": "Verwey", "id": "89", "title": "Software Vulnerability Group"}, {"timestamp": "1284541200", "speakers": [{"name": "Christos Kanellopoulos"}], "location": "Keurzaal", "id": "119", "title": "OLA Workshop"}, {"timestamp": "1284546600", "speakers": [], "location": "Grote zaal", "id": "41", "title": "Lunch"}, {"timestamp": "1284552000", "speakers": [{"name": "Bob Jones"}, {"name": "Alex Hardisty"}], "location": "Yakult Room", "id": "6", "title": "EEF Requirements and the ESFRI projects: Summary and Next Steps"}, {"timestamp": "1284552000", "speakers": [{"name": "Stephen Brewer"}], "location": "Keurzaal", "id": "31", "title": "Virtual Research Communities "}, {"timestamp": "1284552000", "speakers": [{"name": "Peter Szegedi"}, {"name": "Brook Schofield"}], "location": "Mendes da Costa", "id": "32", "title": "TERENA NRENs and Grids Workshop"}, {"timestamp": "1284552000", "speakers": [{"name": "Steven Newhouse"}, {"name": "Silvana Muscella"}, {"name": "Sergio Andreozzi"}], "location": "Graanbeurszaal", "id": "34", "title": "The DCI Projects: Standards Roadmap"}, {"timestamp": "1284552000", "speakers": [{"name": "Vera Hansper"}, {"name": "Ron Trompert"}], "location": "Berlage", "id": "117", "title": "Grid Oversight"}, {"timestamp": "1284552000", "speakers": [{"name": "John Gordon"}], "location": "Verwey", "id": "123", "title": "Accounting Workshop"}, {"timestamp": "1284552000", "speakers": [], "location": "Archief Damrakzijde", "id": "129", "title": "Project Administrative Committee (Closed)"}, {"timestamp": "1284557400", "speakers": [], "location": "Grote zaal", "id": "52", "title": "Coffee / Tea"}, {"timestamp": "1284559200", "speakers": [{"name": "Neil Geddes"}], "location": "Yakult Room", "id": "53", "title": "Data Management Requirements in EGI"}, {"timestamp": "1284559200", "speakers": [{"name": "Peter Szegedi"}, {"name": "Brook Schofield"}], "location": "Mendes da Costa", "id": "32", "title": "TERENA NRENs and Grids Workshop"}, {"timestamp": "1284559200", "speakers": [{"name": "Vera Hansper"}, {"name": "Ron Trompert"}], "location": "Berlage", "id": "117", "title": "Grid Oversight"}, {"timestamp": "1284559200", "speakers": [{"name": "Steven Newhouse"}], "location": "Derkindern", "id": "126", "title": "ESFRI ENV & EGI (Closed)"}, {"timestamp": "1284559200", "speakers": [{"name": "Stephen Brewer"}], "location": "Keurzaal", "id": "31", "title": "Virtual Research Communities "}, {"timestamp": "1284559200", "speakers": [{"name": "John Gordon"}], "location": "Verwey", "id": "123", "title": "Accounting Workshop"}, {"timestamp": "1284559200", "speakers": [{"name": "Catherine Gater"}], "location": "Graanbeurszaal", "id": "127", "title": "Telling your story"}, {"timestamp": "1284559200", "speakers": [{"name": "Isabel Campos Plasencia Campos Plasencia"}, {"name": "John Walsh"}], "location": "Archief Damrakzijde", "id": "131", "title": "Message Passing Interface - Current Status and Future Developments"}, {"timestamp": "1284620400", "speakers": [], "location": "Yakult Room", "id": "63", "title": "Plenary Keynote"}, {"timestamp": "1284620400", "speakers": [], "location": "Archief Damrakzijde", "id": "111", "title": "ESFRI Pilot Project Coordinators"}, {"timestamp": "1284625800", "speakers": [], "location": "Grote zaal", "id": "65", "title": "Coffee / Tea"}, {"timestamp": "1284627600", "speakers": [{"name": "John Kennedy"}, {"name": "Michaela Lechner"}], "location": "Verwey", "id": "19", "title": "Interoperation HPC & HTC Grids"}, {"timestamp": "1284627600", "speakers": [{"name": "Alberto Meglio"}, {"name": "Diana Cresti"}], "location": "Yakult Room", "id": "121", "title": "European Middleware Initiative"}, {"timestamp": "1284627600", "speakers": [{"name": "Steven Newhouse"}], "location": "Mendes da Costa", "id": "66", "title": "EGI-InSPIRE CB (Closed)"}, {"timestamp": "1284627600", "speakers": [{"name": "Jamie Shiers"}], "location": "Berlage", "id": "122", "title": "Heavy User Communities - Requirements"}, {"timestamp": "1284627600", "speakers": [{"name": "Neasan O'Neil"}], "location": "Keurzaal", "id": "67", "title": "Regional Dissemination"}, {"timestamp": "1284627600", "speakers": [{"name": "Alberto Masoni"}, {"name": "Ognjen Prnjat"}, {"name": "Bernard Marechal"}, {"name": "Federico Ruggieri"}], "location": "Graanbeurszaal", "id": "75", "title": "Regional Initiatives"}, {"timestamp": "1284633000", "speakers": [], "location": "Grote zaal", "id": "74", "title": "Lunch"}, {"timestamp": "1284638400", "speakers": [{"name": "Alberto Masoni"}, {"name": "Ognjen Prnjat"}, {"name": "Bernard Marechal"}, {"name": "Federico Ruggieri"}], "location": "Graanbeurszaal", "id": "75", "title": "Regional Initiatives"}, {"timestamp": "1284638400", "speakers": [{"name": "Daniele Cesini"}], "location": "Verwey", "id": "20", "title": "Operational Tools Roadmap"}, {"timestamp": "1284638400", "speakers": [{"name": "David Kelsey"}], "location": "Keurzaal", "id": "55", "title": "Security Policy Group"}, {"timestamp": "1284638400", "speakers": [{"name": "Jamie Shiers"}], "location": "Berlage", "id": "46", "title": "Services for the EGI Heavy User Communities"}, {"timestamp": "1284638400", "speakers": [{"name": "Aake Edlund"}], "location": "Yakult Room", "id": "79", "title": "ECEE"}, {"timestamp": "1284638400", "speakers": [{"name": "Per \u00d6ster"}], "location": "Mendes da Costa", "id": "76", "title": "EGI Council (Closed)"}, {"timestamp": "1284638400", "speakers": [{"name": "Diana Cresti"}], "location": "Derkindern", "id": "128", "title": "European Middleware Initiative - InReach "}, {"timestamp": "1284643800", "speakers": [], "location": "Grote zaal", "id": "85", "title": "Coffee / Tea"}, {"timestamp": "1284645600", "speakers": [{"name": "Mingchao Ma"}], "location": "Keurzaal", "id": "69", "title": "Security Forum - Open Discussions"}, {"timestamp": "1284645600", "speakers": [{"name": "Jamie Shiers"}], "location": "Berlage", "id": "46", "title": "Services for the EGI Heavy User Communities"}, {"timestamp": "1284645600", "speakers": [{"name": "Aake Edlund"}], "location": "Yakult Room", "id": "79", "title": "ECEE"}, {"timestamp": "1284645600", "speakers": [{"name": "Per \u00d6ster"}], "location": "Mendes da Costa", "id": "76", "title": "EGI Council (Closed)"}, {"timestamp": "1284645600", "speakers": [{"name": "Ron Trompert"}, {"name": "Torsten Antoni"}], "location": "Verwey", "id": "120", "title": "EGI Helpdesk - Support, Process and Implementation"}, {"timestamp": "1284645600", "speakers": [{"name": "Alexander Papaspyrou"}], "location": "Graanbeurszaal", "id": "133", "title": "Initiative for Globus in Europe"}, {"timestamp": "1284703200", "speakers": [{"name": "Steven Newhouse"}], "location": "Mendes da Costa", "id": "96", "title": "EGI-InSPIRE PMB (Closed)"}, {"timestamp": "1284706800", "speakers": [{"name": "Gergely Sipos"}], "location": "Mendes da Costa", "id": "78", "title": "NGI User Support Teams"}, {"timestamp": "1284706800", "speakers": [{"name": "Tamas Kiss"}], "location": "Keurzaal", "id": "22", "title": "Supporting EGI user communities with Desktop Grid resources"}, {"timestamp": "1284706800", "speakers": [{"name": "Mario David"}, {"name": "Michaela Lechner"}], "location": "Graanbeurszaal", "id": "100", "title": "Software Rollout to the Production Infrastructure"}, {"timestamp": "1284706800", "speakers": [], "location": "Archief Damrakzijde", "id": "111", "title": "ESFRI Pilot Project Coordinators"}, {"timestamp": "1284712200", "speakers": [], "location": "Grote zaal", "id": "105", "title": "Coffee / Tea"}, {"timestamp": "1284714000", "speakers": [], "location": "Yakult Room", "id": "108", "title": "Closing Keynote"}, {"timestamp": "1284719400", "speakers": [], "location": "Grote zaal", "id": "110", "title": "Lunch"}, {"timestamp": "1284724800", "speakers": [{"name": "Mingchao Ma"}], "location": "Keurzaal", "id": "118", "title": "Security Training"}, {"timestamp": "1284724800", "speakers": [{"name": "Ron Trompert"}, {"name": "Vera Hansper"}], "location": "Graanbeurszaal", "id": "116", "title": "Grid Oversight Training"}, {"timestamp": "1284724800", "speakers": [{"name": "Tamas Kiss"}], "location": "Mendes da Costa", "id": "125", "title": "Using Desktop Grids in an eScience environment"}, {"timestamp": "1284730200", "speakers": [], "location": "Grote zaal", "id": "113", "title": "Coffee / Tea"}, {"timestamp": "1284732000", "speakers": [{"name": "Mingchao Ma"}], "location": "Keurzaal", "id": "118", "title": "Security Training"}, {"timestamp": "1284732000", "speakers": [{"name": "Ron Trompert"}, {"name": "Vera Hansper"}], "location": "Graanbeurszaal", "id": "116", "title": "Grid Oversight Training"}, {"timestamp": "1284732000", "speakers": [{"name": "Tamas Kiss"}], "location": "Mendes da Costa", "id": "125", "title": "Using Desktop Grids in an eScience environment"}]